Metadata-Version: 1.1
Name: docsbackup
Version: 0.0.3
Summary: Downloader for Google documents mentioned in an input file
Home-page: https://github.com/INM-6/docsbackup
Author: Dennis Terhorst
Author-email: d.terhorst@fz-juelich.de
License: BSD
Platform: UNKNOWN
Classifier: Development Status :: 2 - Pre-Alpha
Classifier: Intended Audience :: Science/Research
Classifier: Intended Audience :: End Users/Desktop
Classifier: Intended Audience :: System Administrators
Classifier: License :: OSI Approved :: BSD License
Classifier: Natural Language :: English
Classifier: Operating System :: OS Independent
Classifier: Programming Language :: Python :: 2
Classifier: Programming Language :: Python :: 3
Classifier: Topic :: System :: Archiving :: Backup
